[{
    "logo": "bca",
    "name": "ATM BCA J-Mart",
    "coords": [-8.580254942310175, 116.09779243113528]
}, {
    "logo": "mandiri",
    "name": "ATM Mandiri Drive Thru",
    "coords": [-8.578958634146591, 116.09169413235136]
}, {
    "logo": "mandiri",
    "name": "ATM Mandiri Airlangga",
    "coords": [-8.586006012377227, 116.10095372731654]
}, {
    "logo": "bni",
    "name": "ATM BNI Pendidikan",
    "coords": [-8.5829221391738, 116.10023723546244]
}, {
    "logo": "ntb",
    "name": "ATM NTB Syariah",
    "coords": [-8.584152458716408, 116.09906790087751]
}, {
    "logo": "btn",
    "name": "ATM BTN Airlangga",
    "coords": [-8.58343168777311, 116.10162307502888]
}, {
    "logo": "bni",
    "name": "ATM BNI KCU Mataram",
    "coords": [-8.57890774134776, 116.0913484999638]
}, {
    "logo": "bni",
    "name": "ATM BNI Pemuda",
    "coords": [-8.583796867059611, 116.0960202833974]
}, {
    "logo": "bni",
    "name": "ATM BNI Airlangga",
    "coords": [-8.58812348910072, 116.10036563677085]
}, {
    "logo": "mandiri",
    "name": "ATM Mandiri Airlangga",
    "coords": [-8.581154606496789, 116.09112199996382]
}, {
    "logo": "bni",
    "name": "ATM BNI Plasa Telkom",
    "coords": [-8.58233178478153, 116.09772435885935]
}, {
    "logo": "bri",
    "name": "ATM BRI Airlangga",
    "coords": [-8.585300480499464, 116.10111503002395]
}, {
    "logo": "muamalat",
    "name": "ATM Muamalat Mataram",
    "coords": [-8.581334068056957, 116.10094473795637]
}, {
    "logo": "bca",
    "name": "ATM BCA Alfamart Airlangga",
    "coords": [-8.586285488328452, 116.10085558706513]
}, {
    "logo": "muamalat",
    "name": "ATM Muamalat Pemuda",
    "coords": [-8.582411269011141, 116.09031913580772]
}, {
    "logo": "bri",
    "name": "ATM BRI Pejanggik",
    "coords": [-8.58170962648817, 116.10494137972242]
}, {
    "logo": "ntb",
    "name": "ATM NTB Syariah",
    "coords": [-8.58212930115542, 116.10702305642303]
}, {
    "logo": "bni",
    "name": "ATM BNI & Mandiri Hotel Arianz",
    "coords": [-8.584245519910356, 116.10715111407248]
}]